<annotation>
	<folder>5-leak</folder>
	<filename>img_0683.png</filename>
	<path>/home/gonzalo/CONICET/ERASMUS/RAMI/rami_dataset_convertido/5-leak/img_0683.png</path>
	<source>
		<database>Unknown</database>
	</source>
	<size>
		<width>319</width>
		<height>180</height>
		<depth>3</depth>
	</size>
	<segmented>0</segmented>
	<object>
		<name>pipe</name>
		<pose>Unspecified</pose>
		<truncated>1</truncated>
		<difficult>0</difficult>
		<bndbox>
			<xmin>110</xmin>
			<ymin>97</ymin>
			<xmax>310</xmax>
			<ymax>180</ymax>
		</bndbox>
	</object>
	<object>
		<name>pipe</name>
		<pose>Unspecified</pose>
		<truncated>1</truncated>
		<difficult>0</difficult>
		<bndbox>
			<xmin>48</xmin>
			<ymin>1</ymin>
			<xmax>129</xmax>
			<ymax>74</ymax>
		</bndbox>
	</object>
	<object>
		<name>leak</name>
		<pose>Unspecified</pose>
		<truncated>0</truncated>
		<difficult>0</difficult>
		<bndbox>
			<xmin>82</xmin>
			<ymin>23</ymin>
			<xmax>255</xmax>
			<ymax>152</ymax>
		</bndbox>
	</object>
</annotation>
